lossycount
