Metadata-Version: 2.1
Name: lossycount
Version: 2.0
Summary: UNKNOWN
Home-page: https://github.com/txtcn/lossycount
Author-email: zsp042@gmail.com
License: UNKNOWN
Platform: UNKNOWN
